README.txt
plonetheme.nonzero-configure.zcml
setup.cfg
setup.py
docs/HISTORY.txt
docs/INSTALL.txt
docs/LICENSE.GPL
docs/LICENSE.txt
plonetheme/__init__.py
plonetheme.nonzero.egg-info/PKG-INFO
plonetheme.nonzero.egg-info/SOURCES.txt
plonetheme.nonzero.egg-info/dependency_links.txt
plonetheme.nonzero.egg-info/entry_points.txt
plonetheme.nonzero.egg-info/namespace_packages.txt
plonetheme.nonzero.egg-info/not-zip-safe
plonetheme.nonzero.egg-info/paster_plugins.txt
plonetheme.nonzero.egg-info/requires.txt
plonetheme.nonzero.egg-info/top_level.txt
plonetheme/nonzero/__init__.py
plonetheme/nonzero/configure.zcml
plonetheme/nonzero/profiles.zcml
plonetheme/nonzero/setuphandlers.py
plonetheme/nonzero/skins.zcml
plonetheme/nonzero/tests.py
plonetheme/nonzero/version.txt
plonetheme/nonzero/browser/__init__.py
plonetheme/nonzero/browser/configure.zcml
plonetheme/nonzero/browser/interfaces.py
plonetheme/nonzero/browser/nonzero_logo.pt
plonetheme/nonzero/browser/viewlet.pt
plonetheme/nonzero/browser/viewlets.py
plonetheme/nonzero/profiles/default/actions.xml
plonetheme/nonzero/profiles/default/cssregistry.xml
plonetheme/nonzero/profiles/default/import_steps.xml
plonetheme/nonzero/profiles/default/jsregistry.xml
plonetheme/nonzero/profiles/default/plonetheme.nonzero_various.txt
plonetheme/nonzero/profiles/default/skins.xml
plonetheme/nonzero/profiles/default/viewlets.xml
plonetheme/nonzero/skins/plonetheme_nonzero_custom_images/bullet.gif
plonetheme/nonzero/skins/plonetheme_nonzero_custom_images/n1.gif
plonetheme/nonzero/skins/plonetheme_nonzero_custom_images/n2.gif
plonetheme/nonzero/skins/plonetheme_nonzero_custom_images/n3.gif
plonetheme/nonzero/skins/plonetheme_nonzero_custom_images/n4.gif
plonetheme/nonzero/skins/plonetheme_nonzero_custom_images/n5.gif
plonetheme/nonzero/skins/plonetheme_nonzero_custom_images/n6.gif
plonetheme/nonzero/skins/plonetheme_nonzero_custom_images/spacer.gif
plonetheme/nonzero/skins/plonetheme_nonzero_custom_templates/main_template.pt
plonetheme/nonzero/skins/plonetheme_nonzero_styles/IEFixes.css.dtml
plonetheme/nonzero/skins/plonetheme_nonzero_styles/IEFixes.css.dtml.metadata
plonetheme/nonzero/skins/plonetheme_nonzero_styles/base_properties.props
plonetheme/nonzero/skins/plonetheme_nonzero_styles/columns.css.dtml
plonetheme/nonzero/skins/plonetheme_nonzero_styles/columns.css.dtml.metadata
