Metadata-Version: 1.0
Name: plonetheme.nonzero
Version: 1.0
Summary: A theme for Plone 3 based on the Nonzero design by NodeThirtyThree
Home-page: http://www.emergetec.com
Author: Tim Knapp
Author-email: info@emergetec.com
License: GPL
Keywords: web zope plone theme
Platform: UNKNOWN
Classifier: Framework :: Plone
Classifier: Framework :: Zope2
Classifier: Framework :: Zope3
Classifier: Programming Language :: Python
Classifier: Topic :: Software Development :: Libraries :: Python Modules
